configuracoes_notebooks/__init__.py
configuracoes_notebooks/set_proj_dir/__init__.py
configuracoes_notebooks/set_proj_dir/find_dir.py
configuracoes_notebooks/set_proj_dir/find_git_proj_dir.py
configuracoes_notebooks/set_proj_dir/set_dir_in_path.py
configuracoes_notebooks/set_proj_dir/set_proj_dir.py
configuracoes_notebooks_seplan-0.1.0.dist-info/LICENSE
configuracoes_notebooks_seplan-0.1.0.dist-info/METADATA
configuracoes_notebooks_seplan-0.1.0.dist-info/WHEEL
configuracoes_notebooks_seplan-0.1.0.dist-info/top_level.txt
configuracoes_notebooks_seplan-0.1.0.dist-info/RECORD
